genericserver/__init__.py
genericserver/__main__.py
genericserver/mockserver.py
genericserver/tcpserver.py
genericserver/udpserver.py
genericserver/responders/__init__.py
genericserver/responders/json_responder.py
genericserver/responders/manual.py
genericserver/responders/okresponder.py
genericserver/responders/reflector.py
tests/__init__.py
tests/test_mockserver.py
tests/responders/__init__.py
tests/responders/test_json_responder.py
tests/responders/test_manual_response.py
tests/responders/test_okresponder.py
tests/responders/test_reflector.py
generic_server-1.1.3.dist-info/LICENSE
generic_server-1.1.3.dist-info/METADATA
generic_server-1.1.3.dist-info/WHEEL
generic_server-1.1.3.dist-info/entry_points.txt
generic_server-1.1.3.dist-info/top_level.txt
generic_server-1.1.3.dist-info/RECORD
