Metadata-Version: 2.1
Name: generic-server
Version: 1.1.3
Summary: Python generic TCP/UDP server implementation, with configurable request-response modules (e.g, 'ok', 'reflect', 'json').
Author: Carsten König
License: GNU GPLv3 License
Project-URL: Homepage, https://gitlab.com/ck2go/generic-server
Keywords: mock,testing,Integration tests,server,simulator
Classifier: Development Status :: 4 - Beta
Classifier: Intended Audience :: Developers
Classifier: License :: OSI Approved :: GNU General Public License v3 (GPLv3)
Classifier: Topic :: Software Development
Classifier: Programming Language :: Python
Classifier: Programming Language :: Python :: 3
Classifier: Operating System :: Unix
Classifier: Operating System :: POSIX
Classifier: Operating System :: MacOS
Requires-Python: >=3.10
License-File: LICENSE
